phycv/__init__.py
phycv/page.py
phycv/page_gpu.py
phycv/pst.py
phycv/pst_gpu.py
phycv/utils.py
phycv/vevid.py
phycv/vevid_gpu.py
phycv-1.2.6.dist-info/LICENSE
phycv-1.2.6.dist-info/METADATA
phycv-1.2.6.dist-info/WHEEL
phycv-1.2.6.dist-info/top_level.txt
phycv-1.2.6.dist-info/RECORD
