Metadata-Version: 2.1
Name: phycv
Version: 1.2.6
Summary: physics-inspired computer vision algorithms
Author: Jalali-Lab
Author-email: ucla.photonics.lab@gmail.com
Keywords: python,image processing,computational imaging,computer vision,physics-inspired algorithm
Classifier: Development Status :: 3 - Alpha
Classifier: Intended Audience :: Developers
Classifier: Intended Audience :: Science/Research
Classifier: Programming Language :: Python :: 3
Classifier: Operating System :: Unix
Classifier: Operating System :: MacOS :: MacOS X
Classifier: Operating System :: Microsoft :: Windows
License-File: LICENSE
Requires-Dist: av
Requires-Dist: imageio
Requires-Dist: imageio-ffmpeg
Requires-Dist: kornia
Requires-Dist: matplotlib
Requires-Dist: numpy
Requires-Dist: opencv-python
Requires-Dist: Pillow
Requires-Dist: torch
Requires-Dist: torchvision
